op_cli/__init__.py
op_cli/main.py
op_cli/functions/__init__.py
op_cli/functions/app.py
op_cli-0.0.2.dist-info/METADATA
op_cli-0.0.2.dist-info/WHEEL
op_cli-0.0.2.dist-info/dependency_links.txt
op_cli-0.0.2.dist-info/entry_points.txt
op_cli-0.0.2.dist-info/top_level.txt
op_cli-0.0.2.dist-info/RECORD
