Metadata-Version: 2.1
Name: op-cli
Version: 0.0.2
Summary: A Simple command line
Home-page: https://gitlab.com/oyetoketoby80/elias-cli.git
Author: Oyetoke Toby
Author-email: oyetoketoby80@gmail.com
License: MIT
Download-URL: https://gitlab.com/oyetoketoby80/elias-cli.git
Platform: UNKNOWN
Requires-Python: >=2.7
Requires-Dist: Click (==7.0)
Requires-Dist: requests (==2.22.0)
Requires-Dist: six (==1.13.0)
